{
  "shlok_hindi": [
    "यथा नदीनां बहवोऽम्बुवेगाः",
    "समुद्रमेवाभिमुखा द्रवन्ति ।",
    "तथा तवामी नरलोकवीरा",
    "विशन्ति वक्त्राण्यभिविज्वलन्ति ॥ ११-२८॥"
  ],
  "shlok_hinglish": [
    "yathā nadīnāṃ bahavo’mbuvegāḥ",
    "samudramevābhimukhā dravanti",
    "tathā tavāmī naralokavīrā",
    "viśanti vaktrāṇyabhivijvalanti 11-28"
  ],
  "shlok_english": "Verily, as many torrents of rivers flow towards the ocean, so these heroes in the world of men enter Your flaming mouths.",
  "defs": [
    {
      "def": "yathā",
      "meaning": "as"
    },
    {
      "def": "nadīnāṃ",
      "meaning": "of the rivers"
    },
    {
      "def": "bahavaḥ",
      "meaning": "the many"
    },
    {
      "def": "ambuvegāḥ",
      "meaning": "waves of the waters"
    },
    {
      "def": "samudraṃ",
      "meaning": "the ocean"
    },
    {
      "def": "eva",
      "meaning": "certainly"
    },
    {
      "def": "abhimukhāḥ",
      "meaning": "towards"
    },
    {
      "def": "dravanti",
      "meaning": "glide"
    },
    {
      "def": "tathā",
      "meaning": "similarly"
    },
    {
      "def": "tava",
      "meaning": "Your"
    },
    {
      "def": "amī",
      "meaning": "all these"
    },
    {
      "def": "naralokavīrāḥ",
      "meaning": "kings of human society"
    },
    {
      "def": "viśanti",
      "meaning": "are entering"
    },
    {
      "def": "vaktrāṇi",
      "meaning": "the mouths"
    },
    {
      "def": "abhivijvalanti",
      "meaning": "and are blazing."
    }
  ]
}