{
  "shlok_hindi": [
    "सङ्करो नरकायैव कुलघ्नानां कुलस्य च ।",
    "पतन्ति पितरो ह्येषां लुप्तपिण्डोदकक्रियाः ॥ १-४२॥"
  ],
  "shlok_hinglish": [
    "saṅkaro narakāyaiva kulaghnānāṃ kulasya ca",
    "patanti pitaro hyeṣāṃ luptapiṇḍodakakriyāḥ 1-42"
  ],
  "shlok_english": "Confusion of castes leads the slayer of the family to hell; for their forefathers fall, deprived of the offerings of PINDA (rice-ball) and water (libations) .",
  "defs": [
    {
      "def": "saṅkaraḥ",
      "meaning": "such unwanted children"
    },
    {
      "def": "narakāya",
      "meaning": "make for hellish life"
    },
    {
      "def": "eva",
      "meaning": "certainly"
    },
    {
      "def": "kulaghnānāṃ",
      "meaning": "for those who are killers of the family"
    },
    {
      "def": "kulasya",
      "meaning": "for the family"
    },
    {
      "def": "ca",
      "meaning": "also"
    },
    {
      "def": "patanti",
      "meaning": "fall down"
    },
    {
      "def": "pitaraḥ",
      "meaning": "forefathers"
    },
    {
      "def": "hi",
      "meaning": "certainly"
    },
    {
      "def": "eṣāṃ",
      "meaning": "of them"
    },
    {
      "def": "lupta",
      "meaning": "stopped"
    },
    {
      "def": "piṇḍa",
      "meaning": "of offerings of food"
    },
    {
      "def": "udaka",
      "meaning": "and water"
    },
    {
      "def": "kriyāḥ",
      "meaning": "performances."
    }
  ]
}