{
  "shlok_hindi": [
    "कामक्रोधवियुक्तानां यतीनां यतचेतसाम् ।",
    "अभितो ब्रह्मनिर्वाणं वर्तते विदितात्मनाम् ॥ ५-२६॥"
  ],
  "shlok_hinglish": [
    "kāmakrodhaviyuktānāṃ yatīnāṃ yatacetasām",
    "abhito brahmanirvāṇaṃ vartate viditātmanām 5-26"
  ],
  "shlok_english": "Absolute Freedom (or BRAHMIC Bliss) exists on all sides for those self-controlled ascetics, who are free from desire and anger, who have controlled their thoughts and who have realised the Self.",
  "defs": [
    {
      "def": "kāma",
      "meaning": "from desires"
    },
    {
      "def": "krodha",
      "meaning": "and anger"
    },
    {
      "def": "vimuktānāṃ",
      "meaning": "of those who are liberated"
    },
    {
      "def": "yatīnāṃ",
      "meaning": "of the saintly persons"
    },
    {
      "def": "yatacetasāṃ",
      "meaning": "who have full control over the mind"
    },
    {
      "def": "abhitaḥ",
      "meaning": "assured in the near future"
    },
    {
      "def": "brahmanirvāṇaṃ",
      "meaning": "liberation in the Supreme"
    },
    {
      "def": "vartate",
      "meaning": "is there"
    },
    {
      "def": "viditātmanāṃ",
      "meaning": "of those who are self-realized."
    }
  ]
}